README.rst
setup.py
src/digimat/__init__.py
src/digimat.danfossally.egg-info/PKG-INFO
src/digimat.danfossally.egg-info/SOURCES.txt
src/digimat.danfossally.egg-info/dependency_links.txt
src/digimat.danfossally.egg-info/namespace_packages.txt
src/digimat.danfossally.egg-info/not-zip-safe
src/digimat.danfossally.egg-info/requires.txt
src/digimat.danfossally.egg-info/top_level.txt
src/digimat/danfossally/__init__.py
src/digimat/danfossally/danfoss.py