Metadata-Version: 2.4
Name: digimat.danfossally
Version: 0.1.12
Summary: Digimat DanfossAlly Wrapper
Home-page: https://www.digimat.ch
Author: Frederic Hess
Author-email: fhess@st-sa.ch
License: PSF
Classifier: Development Status :: 4 - Beta
Classifier: Programming Language :: Python :: 3
Requires-Dist: ptable
Requires-Dist: requests
Requires-Dist: setuptools
Dynamic: author
Dynamic: author-email
Dynamic: classifier
Dynamic: description
Dynamic: home-page
Dynamic: license
Dynamic: requires-dist
Dynamic: summary
